src/__init__.py
src/controllers.py
src/main.py
src/utils.py
guedesmoney-1.2.0.dist-info/LICENSE
guedesmoney-1.2.0.dist-info/METADATA
guedesmoney-1.2.0.dist-info/WHEEL
guedesmoney-1.2.0.dist-info/entry_points.txt
guedesmoney-1.2.0.dist-info/top_level.txt
guedesmoney-1.2.0.dist-info/RECORD
