Metadata-Version: 2.1
Name: guedesmoney
Version: 1.2.0
Summary: A CLI interface for interacting with Portal das Finanças automatically and programmatically
Home-page: https://github.com/JoaoGuedes01/scraper_portal_financas
Author: João Guedes
Author-email: joaoguedes.cjp@gmail.com
Keywords: Portal_Das_Finanças CLI Python Typer Selenium Automation
License-File: LICENSE
Requires-Dist: setuptools
Requires-Dist: selenium
Requires-Dist: typer
